LICENSE
MANIFEST.in
README.md
setup.py
djangobuk_envsettings/__init__.py
djangobuk_envsettings/conversion.py
djangobuk_envsettings/utils.py
djangobuk_envsettings.egg-info/PKG-INFO
djangobuk_envsettings.egg-info/SOURCES.txt
djangobuk_envsettings.egg-info/dependency_links.txt
djangobuk_envsettings.egg-info/not-zip-safe
djangobuk_envsettings.egg-info/requires.txt
djangobuk_envsettings.egg-info/top_level.txt