Metadata-Version: 2.1
Name: djangobuk-envsettings
Version: 0.4.1
Home-page: https://github.com/bukdjango/envsettings
Requires-Python: >=3.8
License-File: LICENSE
